CHANGELOG.md
MANIFEST.in
README.md
setup.cfg
setup.py
versioneer.py
src/libreflow/__init__.py
src/libreflow.extensions.runner.tvpaint_playblast.egg-info/PKG-INFO
src/libreflow.extensions.runner.tvpaint_playblast.egg-info/SOURCES.txt
src/libreflow.extensions.runner.tvpaint_playblast.egg-info/dependency_links.txt
src/libreflow.extensions.runner.tvpaint_playblast.egg-info/requires.txt
src/libreflow.extensions.runner.tvpaint_playblast.egg-info/top_level.txt
src/libreflow/extensions/__init__.py
src/libreflow/extensions/runner/__init__.py
src/libreflow/extensions/runner/tvpaint_playblast/__init__.py
src/libreflow/extensions/runner/tvpaint_playblast/_version.py
src/libreflow/extensions/runner/tvpaint_playblast/scripts/__init__.py
src/libreflow/extensions/runner/tvpaint_playblast/scripts/export_layers.py
src/libreflow/extensions/runner/tvpaint_playblast/scripts/fetch_layers.py
src/libreflow/extensions/runner/tvpaint_playblast/scripts/render.py