Metadata-Version: 2.4
Name: libreflow.extensions.runner.tvpaint_playblast
Version: 1.2.2
Home-page: https://gitlab.com/lfs.coop/libreflow/extensions/runner/tvpaint_playblast
Author: LFS
Author-email: libreflow@lfs.coop
License: LGPLv3+
Keywords: kabaret libreflow
Classifier: Programming Language :: Python :: 3
Classifier: Intended Audience :: Developers
Classifier: License :: OSI Approved :: GNU Lesser General Public License v3 or later (LGPLv3+)
Classifier: Operating System :: OS Independent
Requires-Python: >=3.9
Requires-Dist: pytvpaint
Requires-Dist: libreflow>=2.12.7
Dynamic: author
Dynamic: author-email
Dynamic: classifier
Dynamic: description
Dynamic: description-content-type
Dynamic: home-page
Dynamic: keywords
Dynamic: license
Dynamic: requires-dist
Dynamic: requires-python
